{"stat.walkOneCm":190986,"achievement.openInventory":10,"stat.useItem.minecraft.stone":12,"stat.leaveGame":14,"stat.useItem.minecraft.log":76,"stat.damageTaken":480,"stat.useItem.minecraft.anvil":3,"stat.flyOneCm":102916,"stat.deaths":2,"stat.jump":23,"stat.useItem.minecraft.snow":16,"stat.playOneMinute":70960,"stat.fallOneCm":3030,"stat.useItem.minecraft.planks":23,"stat.crouchOneCm":376,"stat.timeSinceDeath":27670,"stat.sprintOneCm":2167,"stat.useItem.minecraft.wooden_slab":3,"achievement.exploreAllBiomes":{"value":0,"progress":["Ocean"]},"stat.useItem.minecraft.fence":22}